yen/__init__.py
yen/__main__.py
yen/cli.py
yen/downloader.py
yen/fallback_release_data.json
yen/github.py
yen/linux_i686_release.json
yen/py.typed
yen-0.6.1.dist-info/LICENSE
yen-0.6.1.dist-info/METADATA
yen-0.6.1.dist-info/WHEEL
yen-0.6.1.dist-info/entry_points.txt
yen-0.6.1.dist-info/top_level.txt
yen-0.6.1.dist-info/RECORD
